odoo/addons/partner_create_format_phone/README.rst
odoo/addons/partner_create_format_phone/__init__.py
odoo/addons/partner_create_format_phone/__manifest__.py
odoo/addons/partner_create_format_phone/i18n/es.po
odoo/addons/partner_create_format_phone/i18n/it.po
odoo/addons/partner_create_format_phone/i18n/partner_create_format_phone.pot
odoo/addons/partner_create_format_phone/models/__init__.py
odoo/addons/partner_create_format_phone/models/res_partner.py
odoo/addons/partner_create_format_phone/readme/CONTRIBUTORS.rst
odoo/addons/partner_create_format_phone/readme/DESCRIPTION.rst
odoo/addons/partner_create_format_phone/static/description/icon.png
odoo/addons/partner_create_format_phone/static/description/index.html
odoo14_addon_partner_create_format_phone-14.0.1.0.1.dev8.dist-info/METADATA
odoo14_addon_partner_create_format_phone-14.0.1.0.1.dev8.dist-info/WHEEL
odoo14_addon_partner_create_format_phone-14.0.1.0.1.dev8.dist-info/top_level.txt
odoo14_addon_partner_create_format_phone-14.0.1.0.1.dev8.dist-info/RECORD
